{
  "parent": "minecraft:recipes/root",
  "rewards": {
    "recipes": [
      "sophisticatedstorage:packing_tape"
    ]
  },
  "criteria": {
    "has_slime": {
      "trigger": "minecraft:inventory_changed",
      "conditions": {
        "items": [
          {
            "tag": "forge:slimeballs"
          }
        ]
      }
    },
    "has_the_recipe": {
      "trigger": "minecraft:recipe_unlocked",
      "conditions": {
        "recipe": "sophisticatedstorage:packing_tape"
      }
    }
  },
  "requirements": [
    [
      "has_slime",
      "has_the_recipe"
    ]
  ]
}