{
  "neoforge:conditions": [
    {
      "type": "neoforge:mod_loaded",
      "modid": "sophisticatedbackpacks"
    },
    {
      "type": "sophisticatedcore:item_enabled",
      "itemRegistryName": "sophisticatedstorage:stack_upgrade_tier_1_plus"
    }
  ],
  "type": "minecraft:crafting_shaped",
  "category": "misc",
  "key": {
    "P": {
      "tag": "minecraft:planks"
    },
    "S": {
      "item": "sophisticatedbackpacks:stack_upgrade_starter_tier"
    }
  },
  "pattern": [
    "PSP",
    " P ",
    "P P"
  ],
  "result": {
    "count": 3,
    "item": "sophisticatedstorage:stack_upgrade_tier_1_plus"
  }
}